auditlogger/__init__.py
auditlogger/admin.py
auditlogger/app_settings.py
auditlogger/apps.py
auditlogger/cloudwatch.py
auditlogger/middleware.py
auditlogger/models.py
auditlogger/run_tests.py
auditlogger/signals.py
auditlogger/tasks.py
auditlogger/tests.py
auditlogger/migrations/0001_initial.py
auditlogger/migrations/__init__.py
django_audit_logger-1.1.0.dist-info/METADATA
django_audit_logger-1.1.0.dist-info/RECORD
django_audit_logger-1.1.0.dist-info/WHEEL
django_audit_logger-1.1.0.dist-info/top_level.txt
