Metadata-Version: 2.1
Name: django-audit-logger
Version: 1.1.0
Summary: A logger to be used internally
Home-page: UNKNOWN
Author: Wend BV
Author-email: info@wend.nl
License: UNKNOWN
Platform: UNKNOWN
Classifier: Programming Language :: Python :: 2.7
Classifier: Programming Language :: Python :: 3.5
Classifier: Programming Language :: Python :: 3.6
Classifier: Programming Language :: Python :: 3.7
Classifier: Programming Language :: Python :: 3.8
Classifier: License :: OSI Approved :: MIT License
Classifier: Operating System :: OS Independent
Requires-Dist: boto3
Requires-Dist: celery
Requires-Dist: django (>=1.4)
Requires-Dist: redis
Requires-Dist: mock; python_version == "2.7"
